{
  "(0, 3238)": [
    {
      "name": "US",
      "label": "location",
      "description": "The United States of America, a country in North America",
      "uuid": "753f915c-70d4-49e1-9bd5-83e75f461e30",
      "score": 0.651049438466591
    },
    {
      "name": "Netherlands",
      "label": "location",
      "description": "A country in Northwestern Europe, known for its high standard of education and innovative approaches to learning",
      "uuid": "c4ff980e-6edd-400f-9c99-951fa0d0c887",
      "score": 0.6499639313709615
    },
    {
      "name": "outreach activities",
      "label": "project",
      "description": "Educational activities that aim to promote learning and motivation in STEM fields by bridging the gap between schools and external institutions",
      "uuid": "dc2088f9-ffb7-41c3-b0a1-856ecfec89de",
      "score": 0.5051356425845568
    }
  ],
  "(2758, 5909)": [
    {
      "name": "outreach",
      "label": "experiment",
      "description": "A program or activity designed to promote awareness and interest in STEM education among students and teachers>",
      "uuid": "dc2088f9-ffb7-41c3-b0a1-856ecfec89de",
      "score": 0.5131643547999667
    },
    {
      "name": "Colleges and universities",
      "label": "provider",
      "description": "Institutions of higher education that offer academic programs, including those in STEM fields>",
      "uuid": "701feec6-f1b3-450c-9df6-75706822256d",
      "score": 0.51061124753173
    },
    {
      "name": "web-based materials",
      "label": "instrument",
      "description": "Digital resources and tools used for educational purposes, including online courses, tutorials, and interactive simulations>",
      "uuid": "cd8bdd2c-a0db-4202-b10d-a1760d834700",
      "score": 0.5705749996784678
    },
    {
      "name": "industrial laboratory",
      "label": "platform",
      "description": "A facility where scientific research and experimentation are conducted, often in collaboration with industry partners>",
      "uuid": "3cbb9f17-ddb1-48d3-a507-786887e485af",
      "score": 0.5217893281541293
    }
  ],
  "(5381, 8408)": [
    {
      "name": "Netherlands",
      "label": "location",
      "description": "A country in Northwestern Europe where the Jet-Net network was launched",
      "uuid": "c4ff980e-6edd-400f-9c99-951fa0d0c887",
      "score": 0.5848867187014364
    },
    {
      "name": "Denmark",
      "label": "location",
      "description": "A country in Northern Europe where the Jet-Net Model was launched in 2012",
      "uuid": "98f7f9f6-90cb-4f52-8bec-8d21dd310c30",
      "score": 0.5581811292467146
    }
  ],
  "(13308, 16663)": [
    {
      "name": "industrial environments",
      "label": "location",
      "description": "Workplaces or settings where scientific and technological principles are applied in real-world contexts",
      "uuid": "07f7ea8e-cf94-4421-923a-539e12dbeb95",
      "score": 0.5017509766899614
    }
  ],
  "(21188, 23990)": [
    {
      "name": "Canada",
      "label": "location",
      "description": "A country in North America where a study on autonomy support in 10th grade science students was conducted",
      "uuid": "d0081284-5cef-484d-b1ee-a6787b197a33",
      "score": 0.5108222779651318
    },
    {
      "name": "Netherlands",
      "label": "location",
      "description": "A country in Europe where nine outreach activities were conducted",
      "uuid": "c4ff980e-6edd-400f-9c99-951fa0d0c887",
      "score": 0.5709954534281104
    }
  ],
  "(23640, 26445)": [
    {
      "name": "outreach activities",
      "label": "project",
      "description": "Educational programs designed to enhance interest, understanding, and views of science among students",
      "uuid": "dc2088f9-ffb7-41c3-b0a1-856ecfec89de",
      "score": 0.5276748237562642
    }
  ],
  "(25937, 29063)": [
    {
      "name": "MRI",
      "label": "instrument",
      "description": "Magnetic Resonance Imaging, a medical imaging technique used to produce detailed images of the internal structures of the body",
      "uuid": "a8cd4c4e-9442-4d08-af4d-af7d544c2d39",
      "score": 0.5620345051394999
    }
  ],
  "(28501, 31601)": [
    {
      "name": "Netherlands",
      "label": "location",
      "description": "A country in Europe where some of the outreach activities took place",
      "uuid": "c4ff980e-6edd-400f-9c99-951fa0d0c887",
      "score": 0.583002324457223
    },
    {
      "name": "US",
      "label": "location",
      "description": "The United States, a country where some of the outreach activities took place",
      "uuid": "753f915c-70d4-49e1-9bd5-83e75f461e30",
      "score": 0.5096827187366345
    }
  ],
  "(31077, 34322)": [
    {
      "name": "MRI project",
      "label": "project",
      "description": "A scientific program or field campaign from which data were collected, focused on studying learning environments and student perceptions",
      "uuid": "a8cd4c4e-9442-4d08-af4d-af7d544c2d39",
      "score": 0.5197906113374462
    },
    {
      "name": "US",
      "label": "location",
      "description": "The United States of America, a country in North America",
      "uuid": "753f915c-70d4-49e1-9bd5-83e75f461e30",
      "score": 0.651049438466591
    },
    {
      "name": "Netherlands",
      "label": "location",
      "description": "A country in Northwestern Europe, where the 'keurig kiezen' project took place",
      "uuid": "c4ff980e-6edd-400f-9c99-951fa0d0c887",
      "score": 0.5850733609774164
    }
  ],
  "(33750, 37374)": [
    {
      "name": "projects",
      "label": "location",
      "description": "A type of outreach activity that involves students working on a task, assignment, or investigation over a period of time",
      "uuid": "fb0b9fcd-5c96-4989-8c64-a479bbed83ab",
      "score": 0.5270354095296645
    }
  ],
  "(39586, 42801)": [
    {
      "name": "experiments",
      "label": "experiment",
      "description": "Hands-on educational activities that allow students to explore scientific concepts and principles through direct experience",
      "uuid": "d69f7457-db31-48ce-b8c2-98058c412bc6",
      "score": 0.530371710001342
    }
  ],
  "(42307, 45758)": [
    {
      "name": "US",
      "label": "location",
      "description": "The United States of America, a country in North America",
      "uuid": "753f915c-70d4-49e1-9bd5-83e75f461e30",
      "score": 0.651049438466591
    },
    {
      "name": "Dutch",
      "label": "location",
      "description": "The Netherlands, a country in Europe",
      "uuid": "c4ff980e-6edd-400f-9c99-951fa0d0c887",
      "score": 0.5616189910986567
    }
  ],
  "(45200, 48240)": [
    {
      "name": "classroom",
      "label": "location",
      "description": "A physical or virtual space where students receive instruction and engage in learning activities, often serving as a traditional setting for education",
      "uuid": "f85293fe-eb9d-491a-bba8-46261a38b9bf",
      "score": 0.5050861580212608
    },
    {
      "name": "Creative Commons",
      "label": "provider",
      "description": "An organization that provides free, standardized licenses for creative works, enabling authors to retain copyright while allowing others to use and share their work",
      "uuid": "95c7e601-fcfe-4fc9-9994-8105a1e11428",
      "score": 0.5462866224810865
    }
  ],
  "(48121, 48240)": [
    {
      "name": "Creative Commons",
      "label": "provider",
      "description": "A non-profit organization that provides free, standardized licenses for creators to make their work available for others to use, share, and build upon",
      "uuid": "95c7e601-fcfe-4fc9-9994-8105a1e11428",
      "score": 0.5514176762224465
    },
    {
      "name": "license",
      "label": "variable",
      "description": "A legal document that grants permission to use, share, or modify a work, such as a creative work or software",
      "uuid": "3c937799-5ee5-4ea3-b7d5-418a625a7872",
      "score": 0.5637072849135324
    }
  ]
}